{
  "report_id": "RPT-2026-05-13-08-22-47",
  "session_id": "ba61e06b-7edc-4b47-847d-d69d1e48187b",
  "user_id": "b7eb2e79-094f-4a1f-bc76-64e4d1c37387",
  "persona_id": "rushed_customer",
  "persona_name": "العميل المستعجل",
  "mode": "training",
  "created_at": "2024-05-24T10:30:00Z",
  "quick_stats": {
    "duration_seconds": 47,
    "duration_formatted": "00:47",
    "total_turns": 3,
    "salesperson_turns": 2,
    "customer_turns": 1,
    "final_customer_emotion": "angry",
    "emotion_improved": false,
    "checkpoints_achieved": 0,
    "checkpoints_total": 6,
    "checkpoint_list": [
      "Rapport Established ❌",
      "Needs Identified ❌",
      "Value Demonstrated ❌",
      "Objection Handled ❌",
      "Closing Signal Recognized ❌",
      "Commitment Achieved ❌"
    ],
    "call_outcome": "customer_disengaged"
  },
  "scores": {
    "overall_score": 5,
    "pass_threshold": 75,
    "status": "failed",
    "points_from_passing": -70,
    "skills": [
      {
        "skill_name": "Rapport Building",
        "skill_key": "rapport_building",
        "score": 5,
        "weight": 0.2,
        "weighted_contribution": 1.0,
        "was_tested": true,
        "summary": "The initial introduction was professional, but an unprofessional comment quickly damaged the connection.",
        "strengths": [
          "Provided a standard, professional self-introduction at the beginning of the call."
        ],
        "areas_to_improve": [
          "Avoid making strange or unprofessional jokes that can confuse and alienate the customer.",
          "Focus on creating a positive and clear first impression."
        ],
        "evidence_turns": [
          0,
          1
        ]
      },
      {
        "skill_name": "Active Listening",
        "skill_key": "active_listening",
        "score": 0,
        "weight": 0.2,
        "weighted_contribution": 0.0,
        "was_tested": true,
        "summary": "A key opportunity was missed by not addressing the customer's direct question about a specific location.",
        "strengths": [],
        "areas_to_improve": [
          "Must listen to the customer's direct questions and address them.",
          "Ignoring a customer's stated need (location preference) shows a lack of attention and can end the call."
        ],
        "evidence_turns": [
          0,
          2
        ]
      },
      {
        "skill_name": "Needs Discovery",
        "skill_key": "needs_discovery",
        "score": 5,
        "weight": 0.23,
        "weighted_contribution": 1.15,
        "was_tested": true,
        "summary": "You successfully asked for the customer's name, but didn't explore their needs further.",
        "strengths": [
          "Successfully asked for and obtained the customer's name."
        ],
        "areas_to_improve": [
          "Failed to ask any discovery questions (e.g., budget, timeline, property type) to understand the customer's needs.",
          "Should have used the customer's initial query about 'التجمع' as a starting point for a deeper discovery conversation."
        ],
        "evidence_turns": [
          0,
          2
        ]
      },
      {
        "skill_name": "Product Knowledge",
        "skill_key": "product_knowledge",
        "score": 0,
        "weight": 0.0,
        "weighted_contribution": 0.0,
        "was_tested": false,
        "summary": "Not tested in this short conversation.",
        "strengths": [],
        "areas_to_improve": [],
        "evidence_turns": []
      },
      {
        "skill_name": "Objection Handling",
        "skill_key": "objection_handling",
        "score": 0,
        "weight": 0.0,
        "weighted_contribution": 0.0,
        "was_tested": false,
        "summary": "The call ended on the customer's objection, so there was no chance to handle it.",
        "strengths": [],
        "areas_to_improve": [
          "The conversation ended immediately after the customer's expression of frustration, so this skill was not truly tested, but the salesperson's actions caused the objection."
        ],
        "evidence_turns": [
          2
        ]
      },
      {
        "skill_name": "Emotional Intelligence",
        "skill_key": "emotional_intelligence",
        "score": 0,
        "weight": 0.2,
        "weighted_contribution": 0.0,
        "was_tested": true,
        "summary": "There was a missed opportunity to notice the customer's confusion and frustration and adapt your approach.",
        "strengths": [],
        "areas_to_improve": [
          "Failed to perceive the customer's negative emotional shift after the comment in Turn 1.",
          "Did not adapt behavior in response to the customer's clear irritation, instead making it worse by ignoring their request."
        ],
        "evidence_turns": [
          1,
          2
        ]
      },
      {
        "skill_name": "Closing Skills",
        "skill_key": "closing_skills",
        "score": 0,
        "weight": 0.0,
        "weighted_contribution": 0.0,
        "was_tested": false,
        "summary": "Not tested in this short conversation.",
        "strengths": [],
        "areas_to_improve": [],
        "evidence_turns": []
      },
      {
        "skill_name": "Communication Clarity",
        "skill_key": "communication_clarity",
        "score": 15,
        "weight": 0.17,
        "weighted_contribution": 2.55,
        "was_tested": true,
        "summary": "The initial greeting was clear, but a subsequent comment was confusing and derailed the conversation.",
        "strengths": [
          "The initial introduction in Turn 0 was clear."
        ],
        "areas_to_improve": [
          "Communication must be professional and easy to understand at all times.",
          "Avoid jargon, slang, or confusing jokes, especially during the critical opening stage of a call."
        ],
        "evidence_turns": [
          0,
          1
        ]
      }
    ],
    "skills_tested": 5,
    "skills_passed": 0,
    "strongest_skill": "Communication Clarity",
    "weakest_skill": "Active Listening"
  },
  "checkpoints": [
    {
      "name": "Rapport Established",
      "achieved": false,
      "icon": "❌",
      "description": "The customer feels comfortable and is willing to engage in conversation.",
      "achieved_at_turn": null,
      "how_achieved": null,
      "why_missed": "A confusing and unprofessional comment in turn 1 immediately created annoyance, preventing rapport.",
      "how_to_achieve": "After your introduction, focus on being clear, professional, and positive. A simple, 'Thanks for your interest, Maged. I can certainly help with that,' would have worked well."
    },
    {
      "name": "Needs Identified",
      "achieved": false,
      "icon": "❌",
      "description": "You have a clear understanding of the customer's primary needs and wants.",
      "achieved_at_turn": null,
      "how_achieved": null,
      "why_missed": "The customer's stated interest in 'التجمع' was ignored, and no follow-up questions were asked to understand their needs better.",
      "how_to_achieve": "When a customer states a preference, use it as a starting point. Try asking: 'Great, what about التجمع interests you most? Are you looking for a specific type of unit?'"
    },
    {
      "name": "Value Demonstrated",
      "achieved": false,
      "icon": "❌",
      "description": "You have connected a feature of your product to a specific customer need.",
      "achieved_at_turn": null,
      "how_achieved": null,
      "why_missed": "The conversation did not progress far enough to discuss any properties or their value.",
      "how_to_achieve": "This checkpoint comes after needs discovery. Once you know what the customer wants (e.g., a 3-bedroom in التجمع), you can then present a property that matches."
    },
    {
      "name": "Objection Handled",
      "achieved": false,
      "icon": "❌",
      "description": "You have successfully addressed a customer's concern or hesitation.",
      "achieved_at_turn": null,
      "how_achieved": null,
      "why_missed": "The customer expressed frustration ('أنا مش جاي أسمع كل حاجة'), but the call ended before it could be addressed.",
      "how_to_achieve": "When a customer is frustrated, the first step is to acknowledge it. A good response would be: 'You're right, I apologize. I got ahead of myself. Let's go back to your question about التجمع.'"
    },
    {
      "name": "Closing Signal Recognized",
      "achieved": false,
      "icon": "❌",
      "description": "You have identified a verbal or non-verbal cue that the customer is ready to move forward.",
      "achieved_at_turn": null,
      "how_achieved": null,
      "why_missed": "The customer was disengaged and frustrated, so no closing signals were given.",
      "how_to_achieve": "Listen for questions like 'What are the next steps?' or 'How soon can I see it?'. These are signals that the customer is interested in proceeding."
    },
    {
      "name": "Commitment Achieved",
      "achieved": false,
      "icon": "❌",
      "description": "You have secured a firm next step, such as a meeting or a follow-up call.",
      "achieved_at_turn": null,
      "how_achieved": null,
      "why_missed": "The call ended prematurely with a frustrated customer.",
      "how_to_achieve": "After demonstrating value and handling objections, you can ask for a commitment. For example: 'Based on our conversation, I have a perfect unit to show you. Are you available for a viewing this week?'"
    }
  ],
  "executive_summary": "This was a challenging practice session, but every call is a learning opportunity! You started with a professional introduction, which is a great foundation. The main focus for next time will be on listening closely to the customer's first question and maintaining a clear, professional tone to build trust from the very beginning.",
  "top_strengths": [
    "Professional Opening: You began the call with a clear and standard self-introduction.",
    "Polite Inquiry: You correctly asked for the customer's name to personalize the conversation.",
    "Clear Initial Delivery: Your voice and initial greeting were easy to understand."
  ],
  "top_improvements": [
    "Active Listening: The customer explicitly asked about 'التجمع', but this was ignored. It's crucial to address the customer's direct questions first.",
    "Maintaining Professionalism: The 'مارش مش ماتش' comment was confusing and unprofessional, which immediately damaged rapport. Stick to clear and respectful communication.",
    "Emotional Awareness: The customer's frustration was not recognized. It's important to notice negative reactions and try to repair the conversation, perhaps by apologizing for the confusion."
  ],
  "turn_feedback": [
    {
      "turn_number": 0,
      "speaker": "salesperson",
      "text": "السلام عليكم معك علي عبدالله من شركة حسن علام... تعرف باسم حضرتك",
      "assessment": "good",
      "tone": "positive",
      "what_was_good": "This is a great start! Your introduction was clear, professional, and you correctly moved to ask for the customer's name. This sets a good initial tone.",
      "what_to_improve": null,
      "suggested_alternative": null,
      "skills_shown": [
        "Rapport Building",
        "Needs Discovery"
      ],
      "is_highlight": false,
      "is_critical_moment": false
    },
    {
      "turn_number": 1,
      "speaker": "salesperson",
      "text": "اسم حضرتك ايه مارش مش ماتش كويس... حضرتك تحب تسمع الوفرز بتاعتنا في مدينتي",
      "assessment": "poor",
      "tone": "constructive",
      "what_was_good": null,
      "what_to_improve": "This turn had two key issues. First, the 'مارش مش ماتش' comment was confusing and unprofessional, which immediately put the customer on the defensive. Second, you ignored the customer's direct question about 'التجمع' and pivoted to 'مدينتي', which showed you weren't listening.",
      "suggested_alternative": "After the customer says 'اسمي ماجد... عندك إيه في التجمع تحديداً؟', a better response would be: 'أهلاً بحضرتك يا أستاذ ماجد. أكيد, عندنا مشاريع ممتازة في التجمع. ممكن أعرف حضرتك بتدور على مساحة معينة أو نوع وحدة معين عشان أقدر أساعدك بشكل أفضل؟'",
      "skills_shown": [
        "Rapport Building",
        "Active Listening",
        "Emotional Intelligence",
        "Communication Clarity"
      ],
      "is_highlight": true,
      "is_critical_moment": true
    }
  ],
  "include_turn_feedback": true,
  "highlight_turns": [
    1
  ],
  "recommended_practice": [
    "Practice the 'Opening': Start a new session and focus only on the first 30 seconds. Your goal is to greet the customer, get their name, and then ask a question directly related to what they just said.",
    "Practice 'Active Listening Drill': In your next session, write down the customer's main request on a piece of paper as soon as they say it. Don't move on until you've addressed that point.",
    "Practice 'Repairing the Conversation': In your next call, if you sense the customer is confused or annoyed, try to fix it immediately. Practice saying, 'My apologies, that wasn't clear. Let me rephrase,' and see how the customer responds."
  ],
  "passed": null,
  "certification_eligible": null,
  "retake_recommended": null,
  "include_raw_analysis": false,
  "raw_analysis": null
}